{
  "version": "3.0.0",
  "fps": 16.47,
  "frames": [
    {
      "frameNum": 0,
      "metrics": {
        "integer_motion2": 0.000000,
        "integer_motion": 0.000000,
        "integer_adm2": 0.922654,
        "integer_adm_scale0": 0.878982,
        "integer_adm_scale1": 0.856141,
        "integer_adm_scale2": 0.932673,
        "integer_adm_scale3": 0.957947,
        "integer_vif_scale0": 0.513731,
        "integer_vif_scale1": 0.865061,
        "integer_vif_scale2": 0.916835,
        "integer_vif_scale3": 0.942761,
        "vmaf": 81.540315
      }
    },
    {
      "frameNum": 1,
      "metrics": {
        "integer_motion2": 1.878132,
        "integer_motion": 1.878132,
        "integer_adm2": 0.912466,
        "integer_adm_scale0": 0.868508,
        "integer_adm_scale1": 0.834988,
        "integer_adm_scale2": 0.924850,
        "integer_adm_scale3": 0.950263,
        "integer_vif_scale0": 0.488899,
        "integer_vif_scale1": 0.839627,
        "integer_vif_scale2": 0.899871,
        "integer_vif_scale3": 0.930691,
        "vmaf": 80.085147
      }
    },
    {
      "frameNum": 2,
      "metrics": {
        "integer_motion2": 3.560523,
        "integer_motion": 4.734058,
        "integer_adm2": 0.920113,
        "integer_adm_scale0": 0.885654,
        "integer_adm_scale1": 0.852967,
        "integer_adm_scale2": 0.923422,
        "integer_adm_scale3": 0.956339,
        "integer_vif_scale0": 0.494843,
        "integer_vif_scale1": 0.836928,
        "integer_vif_scale2": 0.899139,
        "integer_vif_scale3": 0.931606,
        "vmaf": 82.505464
      }
    },
    {
      "frameNum": 3,
      "metrics": {
        "integer_motion2": 3.560523,
        "integer_motion": 3.560523,
        "integer_adm2": 0.920001,
        "integer_adm_scale0": 0.890298,
        "integer_adm_scale1": 0.846856,
        "integer_adm_scale2": 0.931440,
        "integer_adm_scale3": 0.951436,
        "integer_vif_scale0": 0.503415,
        "integer_vif_scale1": 0.839034,
        "integer_vif_scale2": 0.900815,
        "integer_vif_scale3": 0.933146,
        "vmaf": 82.560703
      }
    },
    {
      "frameNum": 4,
      "metrics": {
        "integer_motion2": 3.695960,
        "integer_motion": 3.695960,
        "integer_adm2": 0.927615,
        "integer_adm_scale0": 0.900547,
        "integer_adm_scale1": 0.869665,
        "integer_adm_scale2": 0.926607,
        "integer_adm_scale3": 0.959476,
        "integer_vif_scale0": 0.516611,
        "integer_vif_scale1": 0.850513,
        "integer_vif_scale2": 0.908687,
        "integer_vif_scale3": 0.937921,
        "vmaf": 84.266110
      }
    },
    {
      "frameNum": 5,
      "metrics": {
        "integer_motion2": 4.191709,
        "integer_motion": 4.191709,
        "integer_adm2": 0.923517,
        "integer_adm_scale0": 0.896141,
        "integer_adm_scale1": 0.859831,
        "integer_adm_scale2": 0.925917,
        "integer_adm_scale3": 0.954779,
        "integer_vif_scale0": 0.506444,
        "integer_vif_scale1": 0.841928,
        "integer_vif_scale2": 0.902818,
        "integer_vif_scale3": 0.934640,
        "vmaf": 83.682077
      }
    },
    {
      "frameNum": 6,
      "metrics": {
        "integer_motion2": 3.293571,
        "integer_motion": 6.891036,
        "integer_adm2": 0.915491,
        "integer_adm_scale0": 0.881191,
        "integer_adm_scale1": 0.849220,
        "integer_adm_scale2": 0.920963,
        "integer_adm_scale3": 0.949780,
        "integer_vif_scale0": 0.493316,
        "integer_vif_scale1": 0.835153,
        "integer_vif_scale2": 0.897810,
        "integer_vif_scale3": 0.929865,
        "vmaf": 81.432671
      }
    },
    {
      "frameNum": 7,
      "metrics": {
        "integer_motion2": 3.293571,
        "integer_motion": 3.293571,
        "integer_adm2": 0.920389,
        "integer_adm_scale0": 0.884199,
        "integer_adm_scale1": 0.851352,
        "integer_adm_scale2": 0.928301,
        "integer_adm_scale3": 0.954712,
        "integer_vif_scale0": 0.504632,
        "integer_vif_scale1": 0.846766,
        "integer_vif_scale2": 0.907057,
        "integer_vif_scale3": 0.937775,
        "vmaf": 82.805050
      }
    },
    {
      "frameNum": 8,
      "metrics": {
        "integer_motion2": 3.718864,
        "integer_motion": 3.718864,
        "integer_adm2": 0.917380,
        "integer_adm_scale0": 0.883455,
        "integer_adm_scale1": 0.846988,
        "integer_adm_scale2": 0.920197,
        "integer_adm_scale3": 0.954308,
        "integer_vif_scale0": 0.501673,
        "integer_vif_scale1": 0.834813,
        "integer_vif_scale2": 0.897560,
        "integer_vif_scale3": 0.930261,
        "vmaf": 82.019245
      }
    },
    {
      "frameNum": 9,
      "metrics": {
        "integer_motion2": 4.450656,
        "integer_motion": 4.450656,
        "integer_adm2": 0.920222,
        "integer_adm_scale0": 0.894496,
        "integer_adm_scale1": 0.855624,
        "integer_adm_scale2": 0.923019,
        "integer_adm_scale3": 0.951998,
        "integer_vif_scale0": 0.520866,
        "integer_vif_scale1": 0.847642,
        "integer_vif_scale2": 0.907258,
        "integer_vif_scale3": 0.937337,
        "vmaf": 83.456425
      }
    },
    {
      "frameNum": 10,
      "metrics": {
        "integer_motion2": 5.587420,
        "integer_motion": 7.931529,
        "integer_adm2": 0.920187,
        "integer_adm_scale0": 0.892093,
        "integer_adm_scale1": 0.855913,
        "integer_adm_scale2": 0.919888,
        "integer_adm_scale3": 0.953918,
        "integer_vif_scale0": 0.514358,
        "integer_vif_scale1": 0.837442,
        "integer_vif_scale2": 0.899393,
        "integer_vif_scale3": 0.931262,
        "vmaf": 83.818504
      }
    },
    {
      "frameNum": 11,
      "metrics": {
        "integer_motion2": 4.974410,
        "integer_motion": 5.587420,
        "integer_adm2": 0.924081,
        "integer_adm_scale0": 0.896131,
        "integer_adm_scale1": 0.856092,
        "integer_adm_scale2": 0.927389,
        "integer_adm_scale3": 0.956835,
        "integer_vif_scale0": 0.518777,
        "integer_vif_scale1": 0.835943,
        "integer_vif_scale2": 0.897901,
        "integer_vif_scale3": 0.929110,
        "vmaf": 83.870826
      }
    },
    {
      "frameNum": 12,
      "metrics": {
        "integer_motion2": 4.222470,
        "integer_motion": 4.974410,
        "integer_adm2": 0.920272,
        "integer_adm_scale0": 0.887578,
        "integer_adm_scale1": 0.854703,
        "integer_adm_scale2": 0.931088,
        "integer_adm_scale3": 0.950137,
        "integer_vif_scale0": 0.513508,
        "integer_vif_scale1": 0.845733,
        "integer_vif_scale2": 0.905885,
        "integer_vif_scale3": 0.936508,
        "vmaf": 83.274131
      }
    },
    {
      "frameNum": 13,
      "metrics": {
        "integer_motion2": 4.222470,
        "integer_motion": 4.222470,
        "integer_adm2": 0.916461,
        "integer_adm_scale0": 0.882764,
        "integer_adm_scale1": 0.843119,
        "integer_adm_scale2": 0.930474,
        "integer_adm_scale3": 0.948198,
        "integer_vif_scale0": 0.502514,
        "integer_vif_scale1": 0.836689,
        "integer_vif_scale2": 0.899138,
        "integer_vif_scale3": 0.931894,
        "vmaf": 82.320918
      }
    },
    {
      "frameNum": 14,
      "metrics": {
        "integer_motion2": 5.333560,
        "integer_motion": 8.228974,
        "integer_adm2": 0.924574,
        "integer_adm_scale0": 0.898220,
        "integer_adm_scale1": 0.857450,
        "integer_adm_scale2": 0.927207,
        "integer_adm_scale3": 0.956581,
        "integer_vif_scale0": 0.528944,
        "integer_vif_scale1": 0.845301,
        "integer_vif_scale2": 0.904807,
        "integer_vif_scale3": 0.935819,
        "vmaf": 84.645582
      }
    },
    {
      "frameNum": 15,
      "metrics": {
        "integer_motion2": 5.333560,
        "integer_motion": 5.333560,
        "integer_adm2": 0.930046,
        "integer_adm_scale0": 0.901810,
        "integer_adm_scale1": 0.865665,
        "integer_adm_scale2": 0.935514,
        "integer_adm_scale3": 0.960066,
        "integer_vif_scale0": 0.532781,
        "integer_vif_scale1": 0.851170,
        "integer_vif_scale2": 0.909265,
        "integer_vif_scale3": 0.939437,
        "vmaf": 85.833375
      }
    },
    {
      "frameNum": 16,
      "metrics": {
        "integer_motion2": 5.733433,
        "integer_motion": 5.733433,
        "integer_adm2": 0.924544,
        "integer_adm_scale0": 0.905917,
        "integer_adm_scale1": 0.867170,
        "integer_adm_scale2": 0.917353,
        "integer_adm_scale3": 0.956125,
        "integer_vif_scale0": 0.538738,
        "integer_vif_scale1": 0.841818,
        "integer_vif_scale2": 0.901823,
        "integer_vif_scale3": 0.932931,
        "vmaf": 84.669953
      }
    },
    {
      "frameNum": 17,
      "metrics": {
        "integer_motion2": 5.750442,
        "integer_motion": 5.750442,
        "integer_adm2": 0.918310,
        "integer_adm_scale0": 0.898868,
        "integer_adm_scale1": 0.856928,
        "integer_adm_scale2": 0.915643,
        "integer_adm_scale3": 0.950551,
        "integer_vif_scale0": 0.528353,
        "integer_vif_scale1": 0.841501,
        "integer_vif_scale2": 0.901663,
        "integer_vif_scale3": 0.932555,
        "vmaf": 83.648943
      }
    },
    {
      "frameNum": 18,
      "metrics": {
        "integer_motion2": 5.224123,
        "integer_motion": 8.176215,
        "integer_adm2": 0.926571,
        "integer_adm_scale0": 0.901859,
        "integer_adm_scale1": 0.864901,
        "integer_adm_scale2": 0.927233,
        "integer_adm_scale3": 0.958413,
        "integer_vif_scale0": 0.539454,
        "integer_vif_scale1": 0.857078,
        "integer_vif_scale2": 0.912898,
        "integer_vif_scale3": 0.940986,
        "vmaf": 85.271372
      }
    },
    {
      "frameNum": 19,
      "metrics": {
        "integer_motion2": 5.209447,
        "integer_motion": 5.224123,
        "integer_adm2": 0.925447,
        "integer_adm_scale0": 0.898136,
        "integer_adm_scale1": 0.861223,
        "integer_adm_scale2": 0.934705,
        "integer_adm_scale3": 0.953637,
        "integer_vif_scale0": 0.526976,
        "integer_vif_scale1": 0.846784,
        "integer_vif_scale2": 0.905651,
        "integer_vif_scale3": 0.935871,
        "vmaf": 84.725262
      }
    },
    {
      "frameNum": 20,
      "metrics": {
        "integer_motion2": 4.747527,
        "integer_motion": 5.209447,
        "integer_adm2": 0.924641,
        "integer_adm_scale0": 0.900066,
        "integer_adm_scale1": 0.866553,
        "integer_adm_scale2": 0.931927,
        "integer_adm_scale3": 0.950500,
        "integer_vif_scale0": 0.530977,
        "integer_vif_scale1": 0.849288,
        "integer_vif_scale2": 0.907760,
        "integer_vif_scale3": 0.937380,
        "vmaf": 84.369295
      }
    },
    {
      "frameNum": 21,
      "metrics": {
        "integer_motion2": 4.747527,
        "integer_motion": 4.747527,
        "integer_adm2": 0.926954,
        "integer_adm_scale0": 0.892675,
        "integer_adm_scale1": 0.869793,
        "integer_adm_scale2": 0.928505,
        "integer_adm_scale3": 0.959576,
        "integer_vif_scale0": 0.526397,
        "integer_vif_scale1": 0.854985,
        "integer_vif_scale2": 0.911526,
        "integer_vif_scale3": 0.940339,
        "vmaf": 85.003715
      }
    },
    {
      "frameNum": 22,
      "metrics": {
        "integer_motion2": 3.871309,
        "integer_motion": 6.483058,
        "integer_adm2": 0.919169,
        "integer_adm_scale0": 0.883444,
        "integer_adm_scale1": 0.845040,
        "integer_adm_scale2": 0.917546,
        "integer_adm_scale3": 0.960458,
        "integer_vif_scale0": 0.519142,
        "integer_vif_scale1": 0.842488,
        "integer_vif_scale2": 0.903058,
        "integer_vif_scale3": 0.934359,
        "vmaf": 82.655896
      }
    },
    {
      "frameNum": 23,
      "metrics": {
        "integer_motion2": 3.871309,
        "integer_motion": 3.871309,
        "integer_adm2": 0.917955,
        "integer_adm_scale0": 0.890077,
        "integer_adm_scale1": 0.847572,
        "integer_adm_scale2": 0.921134,
        "integer_adm_scale3": 0.951746,
        "integer_vif_scale0": 0.522395,
        "integer_vif_scale1": 0.842566,
        "integer_vif_scale2": 0.903035,
        "integer_vif_scale3": 0.934593,
        "vmaf": 82.449060
      }
    },
    {
      "frameNum": 24,
      "metrics": {
        "integer_motion2": 3.838790,
        "integer_motion": 4.070196,
        "integer_adm2": 0.927565,
        "integer_adm_scale0": 0.896695,
        "integer_adm_scale1": 0.862139,
        "integer_adm_scale2": 0.933673,
        "integer_adm_scale3": 0.958475,
        "integer_vif_scale0": 0.539540,
        "integer_vif_scale1": 0.856433,
        "integer_vif_scale2": 0.912138,
        "integer_vif_scale3": 0.939874,
        "vmaf": 84.415877
      }
    },
    {
      "frameNum": 25,
      "metrics": {
        "integer_motion2": 3.838790,
        "integer_motion": 3.838790,
        "integer_adm2": 0.916637,
        "integer_adm_scale0": 0.886790,
        "integer_adm_scale1": 0.844338,
        "integer_adm_scale2": 0.927522,
        "integer_adm_scale3": 0.948169,
        "integer_vif_scale0": 0.515131,
        "integer_vif_scale1": 0.840904,
        "integer_vif_scale2": 0.901610,
        "integer_vif_scale3": 0.933416,
        "vmaf": 82.144959
      }
    },
    {
      "frameNum": 26,
      "metrics": {
        "integer_motion2": 3.094733,
        "integer_motion": 5.337606,
        "integer_adm2": 0.916927,
        "integer_adm_scale0": 0.880743,
        "integer_adm_scale1": 0.844670,
        "integer_adm_scale2": 0.924252,
        "integer_adm_scale3": 0.952548,
        "integer_vif_scale0": 0.514873,
        "integer_vif_scale1": 0.842025,
        "integer_vif_scale2": 0.902442,
        "integer_vif_scale3": 0.932864,
        "vmaf": 81.678162
      }
    },
    {
      "frameNum": 27,
      "metrics": {
        "integer_motion2": 2.356897,
        "integer_motion": 3.094733,
        "integer_adm2": 0.912979,
        "integer_adm_scale0": 0.876174,
        "integer_adm_scale1": 0.846763,
        "integer_adm_scale2": 0.923715,
        "integer_adm_scale3": 0.944654,
        "integer_vif_scale0": 0.498095,
        "integer_vif_scale1": 0.836576,
        "integer_vif_scale2": 0.898773,
        "integer_vif_scale3": 0.930367,
        "vmaf": 80.414928
      }
    },
    {
      "frameNum": 28,
      "metrics": {
        "integer_motion2": 2.356897,
        "integer_motion": 2.356897,
        "integer_adm2": 0.921473,
        "integer_adm_scale0": 0.887467,
        "integer_adm_scale1": 0.855027,
        "integer_adm_scale2": 0.928827,
        "integer_adm_scale3": 0.954637,
        "integer_vif_scale0": 0.518917,
        "integer_vif_scale1": 0.857245,
        "integer_vif_scale2": 0.913411,
        "integer_vif_scale3": 0.940547,
        "vmaf": 82.564851
      }
    },
    {
      "frameNum": 29,
      "metrics": {
        "integer_motion2": 2.545404,
        "integer_motion": 2.545404,
        "integer_adm2": 0.917002,
        "integer_adm_scale0": 0.882638,
        "integer_adm_scale1": 0.849681,
        "integer_adm_scale2": 0.926357,
        "integer_adm_scale3": 0.949903,
        "integer_vif_scale0": 0.504846,
        "integer_vif_scale1": 0.842157,
        "integer_vif_scale2": 0.902733,
        "integer_vif_scale3": 0.934076,
        "vmaf": 81.456068
      }
    },
    {
      "frameNum": 30,
      "metrics": {
        "integer_motion2": 3.183681,
        "integer_motion": 5.583871,
        "integer_adm2": 0.923584,
        "integer_adm_scale0": 0.889492,
        "integer_adm_scale1": 0.849681,
        "integer_adm_scale2": 0.939470,
        "integer_adm_scale3": 0.954342,
        "integer_vif_scale0": 0.516189,
        "integer_vif_scale1": 0.842431,
        "integer_vif_scale2": 0.903060,
        "integer_vif_scale3": 0.934618,
        "vmaf": 82.976516
      }
    },
    {
      "frameNum": 31,
      "metrics": {
        "integer_motion2": 3.035978,
        "integer_motion": 3.183681,
        "integer_adm2": 0.928541,
        "integer_adm_scale0": 0.890132,
        "integer_adm_scale1": 0.864120,
        "integer_adm_scale2": 0.932701,
        "integer_adm_scale3": 0.963939,
        "integer_vif_scale0": 0.517795,
        "integer_vif_scale1": 0.857715,
        "integer_vif_scale2": 0.914122,
        "integer_vif_scale3": 0.942477,
        "vmaf": 84.336713
      }
    },
    {
      "frameNum": 32,
      "metrics": {
        "integer_motion2": 2.945833,
        "integer_motion": 3.035978,
        "integer_adm2": 0.922705,
        "integer_adm_scale0": 0.883489,
        "integer_adm_scale1": 0.859165,
        "integer_adm_scale2": 0.935702,
        "integer_adm_scale3": 0.952396,
        "integer_vif_scale0": 0.504853,
        "integer_vif_scale1": 0.841581,
        "integer_vif_scale2": 0.902835,
        "integer_vif_scale3": 0.935409,
        "vmaf": 82.769196
      }
    },
    {
      "frameNum": 33,
      "metrics": {
        "integer_motion2": 2.945833,
        "integer_motion": 2.945833,
        "integer_adm2": 0.917526,
        "integer_adm_scale0": 0.878977,
        "integer_adm_scale1": 0.840743,
        "integer_adm_scale2": 0.929055,
        "integer_adm_scale3": 0.953429,
        "integer_vif_scale0": 0.495626,
        "integer_vif_scale1": 0.836503,
        "integer_vif_scale2": 0.899091,
        "integer_vif_scale3": 0.933105,
        "vmaf": 81.748190
      }
    },
    {
      "frameNum": 34,
      "metrics": {
        "integer_motion2": 2.651046,
        "integer_motion": 4.359957,
        "integer_adm2": 0.929425,
        "integer_adm_scale0": 0.888963,
        "integer_adm_scale1": 0.859099,
        "integer_adm_scale2": 0.938977,
        "integer_adm_scale3": 0.963699,
        "integer_vif_scale0": 0.514188,
        "integer_vif_scale1": 0.855750,
        "integer_vif_scale2": 0.913385,
        "integer_vif_scale3": 0.941737,
        "vmaf": 84.207198
      }
    },
    {
      "frameNum": 35,
      "metrics": {
        "integer_motion2": 2.541334,
        "integer_motion": 2.651046,
        "integer_adm2": 0.923659,
        "integer_adm_scale0": 0.877905,
        "integer_adm_scale1": 0.853198,
        "integer_adm_scale2": 0.933334,
        "integer_adm_scale3": 0.959971,
        "integer_vif_scale0": 0.500918,
        "integer_vif_scale1": 0.844565,
        "integer_vif_scale2": 0.905317,
        "integer_vif_scale3": 0.936466,
        "vmaf": 82.785393
      }
    },
    {
      "frameNum": 36,
      "metrics": {
        "integer_motion2": 2.524203,
        "integer_motion": 2.541334,
        "integer_adm2": 0.928767,
        "integer_adm_scale0": 0.888664,
        "integer_adm_scale1": 0.863047,
        "integer_adm_scale2": 0.938513,
        "integer_adm_scale3": 0.961844,
        "integer_vif_scale0": 0.514327,
        "integer_vif_scale1": 0.857788,
        "integer_vif_scale2": 0.914488,
        "integer_vif_scale3": 0.942988,
        "vmaf": 84.101022
      }
    },
    {
      "frameNum": 37,
      "metrics": {
        "integer_motion2": 2.524203,
        "integer_motion": 2.524203,
        "integer_adm2": 0.921370,
        "integer_adm_scale0": 0.885952,
        "integer_adm_scale1": 0.852110,
        "integer_adm_scale2": 0.929352,
        "integer_adm_scale3": 0.955650,
        "integer_vif_scale0": 0.497008,
        "integer_vif_scale1": 0.841110,
        "integer_vif_scale2": 0.902767,
        "integer_vif_scale3": 0.934999,
        "vmaf": 82.282080
      }
    },
    {
      "frameNum": 38,
      "metrics": {
        "integer_motion2": 2.536583,
        "integer_motion": 4.404058,
        "integer_adm2": 0.917956,
        "integer_adm_scale0": 0.888049,
        "integer_adm_scale1": 0.858842,
        "integer_adm_scale2": 0.921187,
        "integer_adm_scale3": 0.949085,
        "integer_vif_scale0": 0.502326,
        "integer_vif_scale1": 0.841896,
        "integer_vif_scale2": 0.902759,
        "integer_vif_scale3": 0.934758,
        "vmaf": 81.666596
      }
    },
    {
      "frameNum": 39,
      "metrics": {
        "integer_motion2": 2.536583,
        "integer_motion": 2.536583,
        "integer_adm2": 0.925163,
        "integer_adm_scale0": 0.889340,
        "integer_adm_scale1": 0.864924,
        "integer_adm_scale2": 0.932938,
        "integer_adm_scale3": 0.955935,
        "integer_vif_scale0": 0.513270,
        "integer_vif_scale1": 0.858823,
        "integer_vif_scale2": 0.914467,
        "integer_vif_scale3": 0.942905,
        "vmaf": 83.485231
      }
    },
    {
      "frameNum": 40,
      "metrics": {
        "integer_motion2": 2.564130,
        "integer_motion": 2.564130,
        "integer_adm2": 0.920678,
        "integer_adm_scale0": 0.885063,
        "integer_adm_scale1": 0.848545,
        "integer_adm_scale2": 0.931162,
        "integer_adm_scale3": 0.954716,
        "integer_vif_scale0": 0.505836,
        "integer_vif_scale1": 0.842113,
        "integer_vif_scale2": 0.902878,
        "integer_vif_scale3": 0.935326,
        "vmaf": 82.166003
      }
    },
    {
      "frameNum": 41,
      "metrics": {
        "integer_motion2": 2.746504,
        "integer_motion": 2.746504,
        "integer_adm2": 0.921870,
        "integer_adm_scale0": 0.883750,
        "integer_adm_scale1": 0.857619,
        "integer_adm_scale2": 0.931995,
        "integer_adm_scale3": 0.953769,
        "integer_vif_scale0": 0.510735,
        "integer_vif_scale1": 0.844451,
        "integer_vif_scale2": 0.904703,
        "integer_vif_scale3": 0.936004,
        "vmaf": 82.530001
      }
    },
    {
      "frameNum": 42,
      "metrics": {
        "integer_motion2": 2.783268,
        "integer_motion": 5.104914,
        "integer_adm2": 0.923595,
        "integer_adm_scale0": 0.885817,
        "integer_adm_scale1": 0.854495,
        "integer_adm_scale2": 0.938122,
        "integer_adm_scale3": 0.954449,
        "integer_vif_scale0": 0.510642,
        "integer_vif_scale1": 0.848925,
        "integer_vif_scale2": 0.908482,
        "integer_vif_scale3": 0.939159,
        "vmaf": 83.091856
      }
    },
    {
      "frameNum": 43,
      "metrics": {
        "integer_motion2": 2.363803,
        "integer_motion": 2.783268,
        "integer_adm2": 0.925006,
        "integer_adm_scale0": 0.889492,
        "integer_adm_scale1": 0.866377,
        "integer_adm_scale2": 0.931869,
        "integer_adm_scale3": 0.955979,
        "integer_vif_scale0": 0.517976,
        "integer_vif_scale1": 0.857786,
        "integer_vif_scale2": 0.914918,
        "integer_vif_scale3": 0.943439,
        "vmaf": 83.382110
      }
    },
    {
      "frameNum": 44,
      "metrics": {
        "integer_motion2": 2.211998,
        "integer_motion": 2.363803,
        "integer_adm2": 0.919475,
        "integer_adm_scale0": 0.879850,
        "integer_adm_scale1": 0.851284,
        "integer_adm_scale2": 0.928848,
        "integer_adm_scale3": 0.954781,
        "integer_vif_scale0": 0.500116,
        "integer_vif_scale1": 0.843727,
        "integer_vif_scale2": 0.904948,
        "integer_vif_scale3": 0.936559,
        "vmaf": 81.872242
      }
    },
    {
      "frameNum": 45,
      "metrics": {
        "integer_motion2": 2.211998,
        "integer_motion": 2.211998,
        "integer_adm2": 0.915971,
        "integer_adm_scale0": 0.875334,
        "integer_adm_scale1": 0.842380,
        "integer_adm_scale2": 0.930680,
        "integer_adm_scale3": 0.950756,
        "integer_vif_scale0": 0.492737,
        "integer_vif_scale1": 0.840441,
        "integer_vif_scale2": 0.902781,
        "integer_vif_scale3": 0.935828,
        "vmaf": 81.241732
      }
    },
    {
      "frameNum": 46,
      "metrics": {
        "integer_motion2": 3.353195,
        "integer_motion": 4.473829,
        "integer_adm2": 0.928229,
        "integer_adm_scale0": 0.900504,
        "integer_adm_scale1": 0.863776,
        "integer_adm_scale2": 0.935938,
        "integer_adm_scale3": 0.959349,
        "integer_vif_scale0": 0.523930,
        "integer_vif_scale1": 0.856578,
        "integer_vif_scale2": 0.913335,
        "integer_vif_scale3": 0.942084,
        "vmaf": 84.430966
      }
    },
    {
      "frameNum": 47,
      "metrics": {
        "integer_motion2": 2.581351,
        "integer_motion": 3.353195,
        "integer_adm2": 0.921297,
        "integer_adm_scale0": 0.886554,
        "integer_adm_scale1": 0.855300,
        "integer_adm_scale2": 0.931658,
        "integer_adm_scale3": 0.953496,
        "integer_vif_scale0": 0.510889,
        "integer_vif_scale1": 0.843730,
        "integer_vif_scale2": 0.904483,
        "integer_vif_scale3": 0.935749,
        "vmaf": 82.311470
      }
    },
    {
      "frameNum": 48,
      "metrics": {
        "integer_motion2": 1.953578,
        "integer_motion": 2.581351,
        "integer_adm2": 0.922258,
        "integer_adm_scale0": 0.882434,
        "integer_adm_scale1": 0.849314,
        "integer_adm_scale2": 0.930899,
        "integer_adm_scale3": 0.959946,
        "integer_vif_scale0": 0.497025,
        "integer_vif_scale1": 0.844379,
        "integer_vif_scale2": 0.905749,
        "integer_vif_scale3": 0.937320,
        "vmaf": 82.255227
      }
    },
    {
      "frameNum": 49,
      "metrics": {
        "integer_motion2": 1.953578,
        "integer_motion": 1.953578,
        "integer_adm2": 0.928630,
        "integer_adm_scale0": 0.889724,
        "integer_adm_scale1": 0.860932,
        "integer_adm_scale2": 0.933816,
        "integer_adm_scale3": 0.965516,
        "integer_vif_scale0": 0.510803,
        "integer_vif_scale1": 0.855942,
        "integer_vif_scale2": 0.913278,
        "integer_vif_scale3": 0.942838,
        "vmaf": 83.709638
      }
    },
    {
      "frameNum": 50,
      "metrics": {
        "integer_motion2": 2.120864,
        "integer_motion": 3.322741,
        "integer_adm2": 0.922078,
        "integer_adm_scale0": 0.884833,
        "integer_adm_scale1": 0.854077,
        "integer_adm_scale2": 0.928999,
        "integer_adm_scale3": 0.956993,
        "integer_vif_scale0": 0.493514,
        "integer_vif_scale1": 0.841135,
        "integer_vif_scale2": 0.902650,
        "integer_vif_scale3": 0.935163,
        "vmaf": 82.167656
      }
    },
    {
      "frameNum": 51,
      "metrics": {
        "integer_motion2": 1.861112,
        "integer_motion": 2.120864,
        "integer_adm2": 0.921141,
        "integer_adm_scale0": 0.885552,
        "integer_adm_scale1": 0.845122,
        "integer_adm_scale2": 0.934160,
        "integer_adm_scale3": 0.955081,
        "integer_vif_scale0": 0.499304,
        "integer_vif_scale1": 0.843757,
        "integer_vif_scale2": 0.904812,
        "integer_vif_scale3": 0.936682,
        "vmaf": 81.942272
      }
    },
    {
      "frameNum": 52,
      "metrics": {
        "integer_motion2": 1.744460,
        "integer_motion": 1.861112,
        "integer_adm2": 0.927308,
        "integer_adm_scale0": 0.893009,
        "integer_adm_scale1": 0.863882,
        "integer_adm_scale2": 0.938855,
        "integer_adm_scale3": 0.957031,
        "integer_vif_scale0": 0.511271,
        "integer_vif_scale1": 0.856206,
        "integer_vif_scale2": 0.912785,
        "integer_vif_scale3": 0.941880,
        "vmaf": 83.281384
      }
    },
    {
      "frameNum": 53,
      "metrics": {
        "integer_motion2": 1.744460,
        "integer_motion": 1.744460,
        "integer_adm2": 0.921607,
        "integer_adm_scale0": 0.882786,
        "integer_adm_scale1": 0.846576,
        "integer_adm_scale2": 0.936810,
        "integer_adm_scale3": 0.955135,
        "integer_vif_scale0": 0.498433,
        "integer_vif_scale1": 0.843737,
        "integer_vif_scale2": 0.904463,
        "integer_vif_scale3": 0.935693,
        "vmaf": 81.885116
      }
    },
    {
      "frameNum": 54,
      "metrics": {
        "integer_motion2": 2.085445,
        "integer_motion": 3.260042,
        "integer_adm2": 0.923205,
        "integer_adm_scale0": 0.885327,
        "integer_adm_scale1": 0.857109,
        "integer_adm_scale2": 0.940730,
        "integer_adm_scale3": 0.950957,
        "integer_vif_scale0": 0.494734,
        "integer_vif_scale1": 0.841876,
        "integer_vif_scale2": 0.904025,
        "integer_vif_scale3": 0.936416,
        "vmaf": 82.433455
      }
    },
    {
      "frameNum": 55,
      "metrics": {
        "integer_motion2": 2.085445,
        "integer_motion": 2.085445,
        "integer_adm2": 0.929909,
        "integer_adm_scale0": 0.894851,
        "integer_adm_scale1": 0.870011,
        "integer_adm_scale2": 0.937721,
        "integer_adm_scale3": 0.960638,
        "integer_vif_scale0": 0.514621,
        "integer_vif_scale1": 0.857208,
        "integer_vif_scale2": 0.914008,
        "integer_vif_scale3": 0.942697,
        "vmaf": 83.994673
      }
    },
    {
      "frameNum": 56,
      "metrics": {
        "integer_motion2": 2.285628,
        "integer_motion": 2.285628,
        "integer_adm2": 0.922335,
        "integer_adm_scale0": 0.891145,
        "integer_adm_scale1": 0.855441,
        "integer_adm_scale2": 0.933519,
        "integer_adm_scale3": 0.953123,
        "integer_vif_scale0": 0.508429,
        "integer_vif_scale1": 0.844888,
        "integer_vif_scale2": 0.905464,
        "integer_vif_scale3": 0.936571,
        "vmaf": 82.373291
      }
    },
    {
      "frameNum": 57,
      "metrics": {
        "integer_motion2": 2.305022,
        "integer_motion": 2.305022,
        "integer_adm2": 0.923372,
        "integer_adm_scale0": 0.888861,
        "integer_adm_scale1": 0.853869,
        "integer_adm_scale2": 0.931043,
        "integer_adm_scale3": 0.958272,
        "integer_vif_scale0": 0.501860,
        "integer_vif_scale1": 0.843026,
        "integer_vif_scale2": 0.904571,
        "integer_vif_scale3": 0.935977,
        "vmaf": 82.547245
      }
    },
    {
      "frameNum": 58,
      "metrics": {
        "integer_motion2": 2.200620,
        "integer_motion": 3.300693,
        "integer_adm2": 0.926718,
        "integer_adm_scale0": 0.890232,
        "integer_adm_scale1": 0.859477,
        "integer_adm_scale2": 0.936783,
        "integer_adm_scale3": 0.959888,
        "integer_vif_scale0": 0.509930,
        "integer_vif_scale1": 0.856710,
        "integer_vif_scale2": 0.913739,
        "integer_vif_scale3": 0.942071,
        "vmaf": 83.499764
      }
    },
    {
      "frameNum": 59,
      "metrics": {
        "integer_motion2": 2.122530,
        "integer_motion": 2.200620,
        "integer_adm2": 0.922735,
        "integer_adm_scale0": 0.885168,
        "integer_adm_scale1": 0.852588,
        "integer_adm_scale2": 0.935112,
        "integer_adm_scale3": 0.956054,
        "integer_vif_scale0": 0.509425,
        "integer_vif_scale1": 0.850339,
        "integer_vif_scale2": 0.909047,
        "integer_vif_scale3": 0.939664,
        "vmaf": 82.564107
      }
    },
    {
      "frameNum": 60,
      "metrics": {
        "integer_motion2": 2.122530,
        "integer_motion": 2.122530,
        "integer_adm2": 0.921845,
        "integer_adm_scale0": 0.887780,
        "integer_adm_scale1": 0.854358,
        "integer_adm_scale2": 0.937004,
        "integer_adm_scale3": 0.951261,
        "integer_vif_scale0": 0.508612,
        "integer_vif_scale1": 0.848720,
        "integer_vif_scale2": 0.907807,
        "integer_vif_scale3": 0.938010,
        "vmaf": 82.299133
      }
    },
    {
      "frameNum": 61,
      "metrics": {
        "integer_motion2": 2.319354,
        "integer_motion": 2.319354,
        "integer_adm2": 0.921744,
        "integer_adm_scale0": 0.892266,
        "integer_adm_scale1": 0.864726,
        "integer_adm_scale2": 0.926208,
        "integer_adm_scale3": 0.952459,
        "integer_vif_scale0": 0.510028,
        "integer_vif_scale1": 0.853894,
        "integer_vif_scale2": 0.911462,
        "integer_vif_scale3": 0.940866,
        "vmaf": 82.619995
      }
    },
    {
      "frameNum": 62,
      "metrics": {
        "integer_motion2": 3.177308,
        "integer_motion": 4.825446,
        "integer_adm2": 0.925875,
        "integer_adm_scale0": 0.894661,
        "integer_adm_scale1": 0.860176,
        "integer_adm_scale2": 0.934063,
        "integer_adm_scale3": 0.956974,
        "integer_vif_scale0": 0.509024,
        "integer_vif_scale1": 0.840219,
        "integer_vif_scale2": 0.902107,
        "integer_vif_scale3": 0.935149,
        "vmaf": 83.419235
      }
    },
    {
      "frameNum": 63,
      "metrics": {
        "integer_motion2": 3.098553,
        "integer_motion": 3.177308,
        "integer_adm2": 0.919573,
        "integer_adm_scale0": 0.893137,
        "integer_adm_scale1": 0.842590,
        "integer_adm_scale2": 0.922794,
        "integer_adm_scale3": 0.956953,
        "integer_vif_scale0": 0.503090,
        "integer_vif_scale1": 0.840722,
        "integer_vif_scale2": 0.902090,
        "integer_vif_scale3": 0.933752,
        "vmaf": 82.235683
      }
    },
    {
      "frameNum": 64,
      "metrics": {
        "integer_motion2": 3.098553,
        "integer_motion": 3.098553,
        "integer_adm2": 0.926420,
        "integer_adm_scale0": 0.897834,
        "integer_adm_scale1": 0.861855,
        "integer_adm_scale2": 0.927992,
        "integer_adm_scale3": 0.960800,
        "integer_vif_scale0": 0.523498,
        "integer_vif_scale1": 0.855664,
        "integer_vif_scale2": 0.912110,
        "integer_vif_scale3": 0.940649,
        "vmaf": 83.849275
      }
    },
    {
      "frameNum": 65,
      "metrics": {
        "integer_motion2": 3.125720,
        "integer_motion": 3.125720,
        "integer_adm2": 0.915770,
        "integer_adm_scale0": 0.892208,
        "integer_adm_scale1": 0.842328,
        "integer_adm_scale2": 0.925995,
        "integer_adm_scale3": 0.947045,
        "integer_vif_scale0": 0.501014,
        "integer_vif_scale1": 0.836450,
        "integer_vif_scale2": 0.897781,
        "integer_vif_scale3": 0.930718,
        "vmaf": 81.372017
      }
    },
    {
      "frameNum": 66,
      "metrics": {
        "integer_motion2": 2.515913,
        "integer_motion": 4.754227,
        "integer_adm2": 0.915480,
        "integer_adm_scale0": 0.887283,
        "integer_adm_scale1": 0.833759,
        "integer_adm_scale2": 0.926614,
        "integer_adm_scale3": 0.950794,
        "integer_vif_scale0": 0.502084,
        "integer_vif_scale1": 0.843318,
        "integer_vif_scale2": 0.904115,
        "integer_vif_scale3": 0.935677,
        "vmaf": 81.310174
      }
    },
    {
      "frameNum": 67,
      "metrics": {
        "integer_motion2": 2.515913,
        "integer_motion": 2.515913,
        "integer_adm2": 0.922687,
        "integer_adm_scale0": 0.897143,
        "integer_adm_scale1": 0.852527,
        "integer_adm_scale2": 0.924637,
        "integer_adm_scale3": 0.957530,
        "integer_vif_scale0": 0.511486,
        "integer_vif_scale1": 0.856334,
        "integer_vif_scale2": 0.912971,
        "integer_vif_scale3": 0.941235,
        "vmaf": 82.939111
      }
    },
    {
      "frameNum": 68,
      "metrics": {
        "integer_motion2": 2.589187,
        "integer_motion": 2.589187,
        "integer_adm2": 0.917645,
        "integer_adm_scale0": 0.890626,
        "integer_adm_scale1": 0.842959,
        "integer_adm_scale2": 0.918139,
        "integer_adm_scale3": 0.954952,
        "integer_vif_scale0": 0.502645,
        "integer_vif_scale1": 0.839200,
        "integer_vif_scale2": 0.900368,
        "integer_vif_scale3": 0.932214,
        "vmaf": 81.459699
      }
    },
    {
      "frameNum": 69,
      "metrics": {
        "integer_motion2": 2.995582,
        "integer_motion": 2.995582,
        "integer_adm2": 0.917183,
        "integer_adm_scale0": 0.890039,
        "integer_adm_scale1": 0.846739,
        "integer_adm_scale2": 0.914999,
        "integer_adm_scale3": 0.955130,
        "integer_vif_scale0": 0.497454,
        "integer_vif_scale1": 0.837231,
        "integer_vif_scale2": 0.899415,
        "integer_vif_scale3": 0.931526,
        "vmaf": 81.621695
      }
    },
    {
      "frameNum": 70,
      "metrics": {
        "integer_motion2": 1.942050,
        "integer_motion": 4.515101,
        "integer_adm2": 0.919736,
        "integer_adm_scale0": 0.889639,
        "integer_adm_scale1": 0.846477,
        "integer_adm_scale2": 0.923524,
        "integer_adm_scale3": 0.956362,
        "integer_vif_scale0": 0.495985,
        "integer_vif_scale1": 0.842721,
        "integer_vif_scale2": 0.904956,
        "integer_vif_scale3": 0.936686,
        "vmaf": 81.780516
      }
    },
    {
      "frameNum": 71,
      "metrics": {
        "integer_motion2": 1.792622,
        "integer_motion": 1.942050,
        "integer_adm2": 0.919091,
        "integer_adm_scale0": 0.892274,
        "integer_adm_scale1": 0.848895,
        "integer_adm_scale2": 0.923078,
        "integer_adm_scale3": 0.953643,
        "integer_vif_scale0": 0.497165,
        "integer_vif_scale1": 0.850580,
        "integer_vif_scale2": 0.909698,
        "integer_vif_scale3": 0.938963,
        "vmaf": 81.761298
      }
    },
    {
      "frameNum": 72,
      "metrics": {
        "integer_motion2": 1.792622,
        "integer_motion": 1.792622,
        "integer_adm2": 0.913563,
        "integer_adm_scale0": 0.888080,
        "integer_adm_scale1": 0.840207,
        "integer_adm_scale2": 0.917270,
        "integer_adm_scale3": 0.949088,
        "integer_vif_scale0": 0.499744,
        "integer_vif_scale1": 0.843186,
        "integer_vif_scale2": 0.903792,
        "integer_vif_scale3": 0.935373,
        "vmaf": 80.514003
      }
    },
    {
      "frameNum": 73,
      "metrics": {
        "integer_motion2": 2.348718,
        "integer_motion": 2.348718,
        "integer_adm2": 0.921862,
        "integer_adm_scale0": 0.897633,
        "integer_adm_scale1": 0.858332,
        "integer_adm_scale2": 0.926403,
        "integer_adm_scale3": 0.952374,
        "integer_vif_scale0": 0.511750,
        "integer_vif_scale1": 0.851501,
        "integer_vif_scale2": 0.909319,
        "integer_vif_scale3": 0.938997,
        "vmaf": 82.505681
      }
    },
    {
      "frameNum": 74,
      "metrics": {
        "integer_motion2": 3.849561,
        "integer_motion": 5.535573,
        "integer_adm2": 0.921093,
        "integer_adm_scale0": 0.904530,
        "integer_adm_scale1": 0.857159,
        "integer_adm_scale2": 0.914413,
        "integer_adm_scale3": 0.955319,
        "integer_vif_scale0": 0.509442,
        "integer_vif_scale1": 0.838433,
        "integer_vif_scale2": 0.899884,
        "integer_vif_scale3": 0.931907,
        "vmaf": 82.822365
      }
    },
    {
      "frameNum": 75,
      "metrics": {
        "integer_motion2": 3.849561,
        "integer_motion": 3.849561,
        "integer_adm2": 0.921505,
        "integer_adm_scale0": 0.909802,
        "integer_adm_scale1": 0.855502,
        "integer_adm_scale2": 0.919711,
        "integer_adm_scale3": 0.951644,
        "integer_vif_scale0": 0.521686,
        "integer_vif_scale1": 0.842072,
        "integer_vif_scale2": 0.902642,
        "integer_vif_scale3": 0.934695,
        "vmaf": 83.040165
      }
    },
    {
      "frameNum": 76,
      "metrics": {
        "integer_motion2": 3.987387,
        "integer_motion": 3.987387,
        "integer_adm2": 0.928075,
        "integer_adm_scale0": 0.914730,
        "integer_adm_scale1": 0.868615,
        "integer_adm_scale2": 0.921570,
        "integer_adm_scale3": 0.959520,
        "integer_vif_scale0": 0.526692,
        "integer_vif_scale1": 0.854313,
        "integer_vif_scale2": 0.910617,
        "integer_vif_scale3": 0.939676,
        "vmaf": 84.619703
      }
    },
    {
      "frameNum": 77,
      "metrics": {
        "integer_motion2": 4.025809,
        "integer_motion": 4.025809,
        "integer_adm2": 0.923048,
        "integer_adm_scale0": 0.912854,
        "integer_adm_scale1": 0.859654,
        "integer_adm_scale2": 0.925044,
        "integer_adm_scale3": 0.949538,
        "integer_vif_scale0": 0.518450,
        "integer_vif_scale1": 0.837912,
        "integer_vif_scale2": 0.898864,
        "integer_vif_scale3": 0.931527,
        "vmaf": 83.191107
      }
    },
    {
      "frameNum": 78,
      "metrics": {
        "integer_motion2": 3.461474,
        "integer_motion": 5.979176,
        "integer_adm2": 0.919876,
        "integer_adm_scale0": 0.907235,
        "integer_adm_scale1": 0.851844,
        "integer_adm_scale2": 0.915242,
        "integer_adm_scale3": 0.953417,
        "integer_vif_scale0": 0.497996,
        "integer_vif_scale1": 0.831770,
        "integer_vif_scale2": 0.896427,
        "integer_vif_scale3": 0.931137,
        "vmaf": 82.337709
      }
    },
    {
      "frameNum": 79,
      "metrics": {
        "integer_motion2": 3.154397,
        "integer_motion": 3.461474,
        "integer_adm2": 0.915785,
        "integer_adm_scale0": 0.901567,
        "integer_adm_scale1": 0.843352,
        "integer_adm_scale2": 0.918397,
        "integer_adm_scale3": 0.947111,
        "integer_vif_scale0": 0.499431,
        "integer_vif_scale1": 0.833387,
        "integer_vif_scale2": 0.896576,
        "integer_vif_scale3": 0.930074,
        "vmaf": 81.360677
      }
    },
    {
      "frameNum": 80,
      "metrics": {
        "integer_motion2": 3.011081,
        "integer_motion": 3.154397,
        "integer_adm2": 0.923389,
        "integer_adm_scale0": 0.900530,
        "integer_adm_scale1": 0.852028,
        "integer_adm_scale2": 0.926515,
        "integer_adm_scale3": 0.956119,
        "integer_vif_scale0": 0.504600,
        "integer_vif_scale1": 0.850113,
        "integer_vif_scale2": 0.908404,
        "integer_vif_scale3": 0.938394,
        "vmaf": 83.172265
      }
    },
    {
      "frameNum": 81,
      "metrics": {
        "integer_motion2": 3.011081,
        "integer_motion": 3.011081,
        "integer_adm2": 0.916359,
        "integer_adm_scale0": 0.891319,
        "integer_adm_scale1": 0.841631,
        "integer_adm_scale2": 0.914273,
        "integer_adm_scale3": 0.953701,
        "integer_vif_scale0": 0.494536,
        "integer_vif_scale1": 0.832042,
        "integer_vif_scale2": 0.895370,
        "integer_vif_scale3": 0.929591,
        "vmaf": 81.340405
      }
    },
    {
      "frameNum": 82,
      "metrics": {
        "integer_motion2": 3.260876,
        "integer_motion": 5.505949,
        "integer_adm2": 0.916634,
        "integer_adm_scale0": 0.891627,
        "integer_adm_scale1": 0.832507,
        "integer_adm_scale2": 0.931100,
        "integer_adm_scale3": 0.948146,
        "integer_vif_scale0": 0.490520,
        "integer_vif_scale1": 0.831411,
        "integer_vif_scale2": 0.894704,
        "integer_vif_scale3": 0.928674,
        "vmaf": 81.506494
      }
    },
    {
      "frameNum": 83,
      "metrics": {
        "integer_motion2": 3.260876,
        "integer_motion": 3.260876,
        "integer_adm2": 0.922962,
        "integer_adm_scale0": 0.894403,
        "integer_adm_scale1": 0.852966,
        "integer_adm_scale2": 0.934530,
        "integer_adm_scale3": 0.952013,
        "integer_vif_scale0": 0.509455,
        "integer_vif_scale1": 0.847581,
        "integer_vif_scale2": 0.906406,
        "integer_vif_scale3": 0.937338,
        "vmaf": 83.151092
      }
    },
    {
      "frameNum": 84,
      "metrics": {
        "integer_motion2": 3.388842,
        "integer_motion": 3.421763,
        "integer_adm2": 0.918286,
        "integer_adm_scale0": 0.889094,
        "integer_adm_scale1": 0.837937,
        "integer_adm_scale2": 0.931645,
        "integer_adm_scale3": 0.951075,
        "integer_vif_scale0": 0.494003,
        "integer_vif_scale1": 0.833697,
        "integer_vif_scale2": 0.896876,
        "integer_vif_scale3": 0.930205,
        "vmaf": 81.976594
      }
    },
    {
      "frameNum": 85,
      "metrics": {
        "integer_motion2": 3.388842,
        "integer_motion": 3.388842,
        "integer_adm2": 0.919123,
        "integer_adm_scale0": 0.893976,
        "integer_adm_scale1": 0.834383,
        "integer_adm_scale2": 0.924417,
        "integer_adm_scale3": 0.958035,
        "integer_vif_scale0": 0.498203,
        "integer_vif_scale1": 0.836133,
        "integer_vif_scale2": 0.898697,
        "integer_vif_scale3": 0.932041,
        "vmaf": 82.229928
      }
    },
    {
      "frameNum": 86,
      "metrics": {
        "integer_motion2": 2.610186,
        "integer_motion": 4.807375,
        "integer_adm2": 0.921952,
        "integer_adm_scale0": 0.895607,
        "integer_adm_scale1": 0.855541,
        "integer_adm_scale2": 0.921066,
        "integer_adm_scale3": 0.956663,
        "integer_vif_scale0": 0.499786,
        "integer_vif_scale1": 0.845063,
        "integer_vif_scale2": 0.904279,
        "integer_vif_scale3": 0.934756,
        "vmaf": 82.412929
      }
    },
    {
      "frameNum": 87,
      "metrics": {
        "integer_motion2": 2.421423,
        "integer_motion": 2.610186,
        "integer_adm2": 0.917037,
        "integer_adm_scale0": 0.885636,
        "integer_adm_scale1": 0.844119,
        "integer_adm_scale2": 0.919083,
        "integer_adm_scale3": 0.953166,
        "integer_vif_scale0": 0.496754,
        "integer_vif_scale1": 0.835870,
        "integer_vif_scale2": 0.897601,
        "integer_vif_scale3": 0.928808,
        "vmaf": 81.034365
      }
    },
    {
      "frameNum": 88,
      "metrics": {
        "integer_motion2": 2.264529,
        "integer_motion": 2.421423,
        "integer_adm2": 0.917919,
        "integer_adm_scale0": 0.890814,
        "integer_adm_scale1": 0.838761,
        "integer_adm_scale2": 0.918986,
        "integer_adm_scale3": 0.956284,
        "integer_vif_scale0": 0.495624,
        "integer_vif_scale1": 0.835157,
        "integer_vif_scale2": 0.896997,
        "integer_vif_scale3": 0.929496,
        "vmaf": 81.121263
      }
    },
    {
      "frameNum": 89,
      "metrics": {
        "integer_motion2": 2.264529,
        "integer_motion": 2.264529,
        "integer_adm2": 0.922089,
        "integer_adm_scale0": 0.895393,
        "integer_adm_scale1": 0.855238,
        "integer_adm_scale2": 0.927136,
        "integer_adm_scale3": 0.953357,
        "integer_vif_scale0": 0.499868,
        "integer_vif_scale1": 0.847651,
        "integer_vif_scale2": 0.906513,
        "integer_vif_scale3": 0.936696,
        "vmaf": 82.364605
      }
    },
    {
      "frameNum": 90,
      "metrics": {
        "integer_motion2": 2.668813,
        "integer_motion": 4.080138,
        "integer_adm2": 0.917557,
        "integer_adm_scale0": 0.896057,
        "integer_adm_scale1": 0.841742,
        "integer_adm_scale2": 0.922234,
        "integer_adm_scale3": 0.951478,
        "integer_vif_scale0": 0.494267,
        "integer_vif_scale1": 0.832307,
        "integer_vif_scale2": 0.895286,
        "integer_vif_scale3": 0.928675,
        "vmaf": 81.261534
      }
    },
    {
      "frameNum": 91,
      "metrics": {
        "integer_motion2": 2.668813,
        "integer_motion": 2.668813,
        "integer_adm2": 0.916106,
        "integer_adm_scale0": 0.893544,
        "integer_adm_scale1": 0.839049,
        "integer_adm_scale2": 0.922528,
        "integer_adm_scale3": 0.949099,
        "integer_vif_scale0": 0.491401,
        "integer_vif_scale1": 0.830785,
        "integer_vif_scale2": 0.894331,
        "integer_vif_scale3": 0.927631,
        "vmaf": 80.958199
      }
    },
    {
      "frameNum": 92,
      "metrics": {
        "integer_motion2": 2.917204,
        "integer_motion": 2.917204,
        "integer_adm2": 0.923218,
        "integer_adm_scale0": 0.896539,
        "integer_adm_scale1": 0.858152,
        "integer_adm_scale2": 0.919933,
        "integer_adm_scale3": 0.958830,
        "integer_vif_scale0": 0.496338,
        "integer_vif_scale1": 0.842349,
        "integer_vif_scale2": 0.903069,
        "integer_vif_scale3": 0.933422,
        "vmaf": 82.755376
      }
    },
    {
      "frameNum": 93,
      "metrics": {
        "integer_motion2": 3.229335,
        "integer_motion": 3.229335,
        "integer_adm2": 0.921319,
        "integer_adm_scale0": 0.897286,
        "integer_adm_scale1": 0.851424,
        "integer_adm_scale2": 0.927993,
        "integer_adm_scale3": 0.951254,
        "integer_vif_scale0": 0.496708,
        "integer_vif_scale1": 0.834284,
        "integer_vif_scale2": 0.896706,
        "integer_vif_scale3": 0.929602,
        "vmaf": 82.326355
      }
    },
    {
      "frameNum": 94,
      "metrics": {
        "integer_motion2": 3.223832,
        "integer_motion": 5.438779,
        "integer_adm2": 0.919885,
        "integer_adm_scale0": 0.891518,
        "integer_adm_scale1": 0.843132,
        "integer_adm_scale2": 0.928235,
        "integer_adm_scale3": 0.953039,
        "integer_vif_scale0": 0.492846,
        "integer_vif_scale1": 0.828711,
        "integer_vif_scale2": 0.893219,
        "integer_vif_scale3": 0.925895,
        "vmaf": 81.844867
      }
    },
    {
      "frameNum": 95,
      "metrics": {
        "integer_motion2": 3.223832,
        "integer_motion": 3.223832,
        "integer_adm2": 0.916757,
        "integer_adm_scale0": 0.895708,
        "integer_adm_scale1": 0.856632,
        "integer_adm_scale2": 0.910233,
        "integer_adm_scale3": 0.951332,
        "integer_vif_scale0": 0.492417,
        "integer_vif_scale1": 0.833345,
        "integer_vif_scale2": 0.897623,
        "integer_vif_scale3": 0.930664,
        "vmaf": 81.663584
      }
    }
  ],
  "pooled_metrics": {
    "integer_motion2": {
      "min": 0.000000,
      "max": 5.750442,
      "mean": 3.081096,
      "harmonic_mean": 2.793464
    },
    "integer_motion": {
      "min": 0.000000,
      "max": 8.228974,
      "mean": 3.665496,
      "harmonic_mean": 3.185293
    },
    "integer_adm2": {
      "min": 0.912466,
      "max": 0.930046,
      "mean": 0.921419,
      "harmonic_mean": 0.921410
    },
    "integer_adm_scale0": {
      "min": 0.868508,
      "max": 0.914730,
      "mean": 0.891096,
      "harmonic_mean": 0.891063
    },
    "integer_adm_scale1": {
      "min": 0.832507,
      "max": 0.870011,
      "mean": 0.852904,
      "harmonic_mean": 0.852861
    },
    "integer_adm_scale2": {
      "min": 0.910233,
      "max": 0.940730,
      "mean": 0.927503,
      "harmonic_mean": 0.927479
    },
    "integer_adm_scale3": {
      "min": 0.944654,
      "max": 0.965516,
      "mean": 0.954561,
      "harmonic_mean": 0.954553
    },
    "integer_vif_scale0": {
      "min": 0.488899,
      "max": 0.539540,
      "mean": 0.508046,
      "harmonic_mean": 0.507952
    },
    "integer_vif_scale1": {
      "min": 0.828711,
      "max": 0.865061,
      "mean": 0.844280,
      "harmonic_mean": 0.844245
    },
    "integer_vif_scale2": {
      "min": 0.893219,
      "max": 0.916835,
      "mean": 0.904430,
      "harmonic_mean": 0.904412
    },
    "integer_vif_scale3": {
      "min": 0.925895,
      "max": 0.943439,
      "mean": 0.935495,
      "harmonic_mean": 0.935486
    },
    "vmaf": {
      "min": 80.085147,
      "max": 85.833375,
      "mean": 82.664608,
      "harmonic_mean": 82.648990
    }
  },
  "aggregate_metrics": {
  }
}
